dgtalVersion.py
dgtal/__init__.py
dgtal/_dgtal.cpython-39-x86_64-linux-gnu.so
dgtal/tables/isthmusicityOne_table26_6.zlib
dgtal/tables/isthmusicityTwo_table26_6.zlib
dgtal/tables/isthmusicity_table26_6.zlib
dgtal/tables/simplicity_table18_6.zlib
dgtal/tables/simplicity_table26_6.zlib
dgtal/tables/simplicity_table4_8.zlib
dgtal/tables/simplicity_table6_18.zlib
dgtal/tables/simplicity_table6_26.zlib
dgtal/tables/simplicity_table8_4.zlib
DGtal-2.0.0.dist-info/METADATA
DGtal-2.0.0.dist-info/WHEEL
DGtal-2.0.0.dist-info/top_level.txt
DGtal-2.0.0.dist-info/RECORD
