Metadata-Version: 2.1
Name: DGtal
Version: 2.0.0
Summary: Digital Geometry Tools and Algorithm Library
Home-page: https://github.com/DGtal-team/DGtal
Author: David Coeurjolly
Author-email: david.coeurjolly@cnrs.fr
License: LGPLv3
Download-URL: https://github.com/DGtal-team/DGtal
Keywords: DGtal image digital topology processing
Platform: UNKNOWN
Classifier: License :: OSI Approved :: GNU Lesser General Public License v3 (LGPLv3)
Classifier: Programming Language :: Python
Classifier: Programming Language :: C++
Classifier: Development Status :: 4 - Beta
Classifier: Intended Audience :: Developers
Classifier: Intended Audience :: Education
Classifier: Intended Audience :: Science/Research
Classifier: Topic :: Scientific/Engineering
Classifier: Topic :: Scientific/Engineering :: Information Analysis
Classifier: Topic :: Software Development :: Libraries
Classifier: Operating System :: Microsoft :: Windows
Classifier: Operating System :: POSIX
Classifier: Operating System :: Unix
Classifier: Operating System :: MacOS
